betteraiohttp/__init__.py
betteraiohttp/client.py
betteraiohttp/errors.py
betteraiohttp-0.2.1.dist-info/LICENSE
betteraiohttp-0.2.1.dist-info/METADATA
betteraiohttp-0.2.1.dist-info/WHEEL
betteraiohttp-0.2.1.dist-info/top_level.txt
betteraiohttp-0.2.1.dist-info/RECORD
