Metadata-Version: 2.1
Name: betteraiohttp
Version: 0.2.1
Summary: A better version of aiohttp that allows for url filtering and rickroll detection.
Home-page: https://github.com/BobDotCom/betteraiohttp
Author: BobDotCom
Author-email: bobdotcomgt@gmail.com
License: GPL
Download-URL: https://github.com/BobDotCom/betteraiohttp/releases
Project-URL: Documentation, https://betteraiohttp.readthedocs.io/en/latest/index.html
Project-URL: Source, https://github.com/BobDotCom/betteraiohttp
Project-URL: Tracker, https://github.com/BobDotCom/betteraiohttp/issues
Platform: UNKNOWN
Classifier: Programming Language :: Python :: 3
Classifier: License :: OSI Approved :: GNU General Public License v3 (GPLv3)
Classifier: Operating System :: OS Independent
Requires-Python: >=3.6
Requires-Dist: url-parser
Requires-Dist: aiohttp
